{"comments":null,"declarations":[{"children":[],"comments":"The `<menu>` tag in HTML, represents a group of commands that a user can perform or activate.\n#### Example:\n```purescript\nmenu { type: \"context\", label: \"My Menu\" }\n```\n\nCommon attributes:\n| Attribute | Type     | Example        | Description |\n|-----------|----------|----------------|-------------|\n| `type`    | `String` | `\"context\"`    | Type of menu. |\n| `label`   | `String` | `\"My Menu\"`    | Label for the menu. |\n","info":{"declType":"value","type":{"annotation":[],"contents":[{"annotation":[],"contents":[["Yoga","React","DOM","Internal"],"FFIComponent_"],"tag":"TypeConstructor"},{"annotation":[],"contents":[["Yoga","React","DOM","HTML","Menu"],"MenuAttributes"],"tag":"TypeConstructor"}],"tag":"TypeApp"}},"kind":null,"sourceSpan":{"end":[20,37],"name":".spago/p/yoga-react-dom-1.0.3/src/Yoga/React/DOM/HTML/Menu.purs","start":[20,1]},"title":"menu"}],"name":"Yoga.React.DOM.HTML.Menu","reExports":[]}