{"comments":"This module defines safe DOM event function and property accessors.\n","declarations":[{"children":[],"comments":"Create a capturing\\* `EventHandler` to send an action when an event occurs. For\nmore complicated event handlers requiring `Effect`, use `handler` from `React.Basic.Events`.\n\n__\\*calls `preventDefault` and `stopPropagation`__\n\n__*See also:* `update`, `capture_`, `monitor`, `React.Basic.Events`__\n","info":{"declType":"value","type":{"annotation":[],"contents":{"identifier":"a","kind":null,"skolem":null,"type":{"annotation":[],"contents":[{"annotation":[],"contents":[{"annotation":[],"contents":[["Prim"],"Function"],"tag":"TypeConstructor"},{"annotation":[],"contents":[{"annotation":[],"contents":[{"annotation":[],"contents":[["React","Basic","Events"],"EventFn"],"tag":"TypeConstructor"},{"annotation":[],"contents":[["React","Basic","Events"],"SyntheticEvent"],"tag":"TypeConstructor"}],"tag":"TypeApp"},{"annotation":[],"contents":"a","tag":"TypeVar"}],"tag":"TypeApp"}],"tag":"TypeApp"},{"annotation":[],"contents":[{"annotation":[],"contents":[{"annotation":[],"contents":[["Prim"],"Function"],"tag":"TypeConstructor"},{"annotation":[],"contents":{"annotation":[],"contents":[{"annotation":[],"contents":[{"annotation":[],"contents":[["Prim"],"Function"],"tag":"TypeConstructor"},{"annotation":[],"contents":"a","tag":"TypeVar"}],"tag":"TypeApp"},{"annotation":[],"contents":[{"annotation":[],"contents":[["Effect"],"Effect"],"tag":"TypeConstructor"},{"annotation":[],"contents":[["Data","Unit"],"Unit"],"tag":"TypeConstructor"}],"tag":"TypeApp"}],"tag":"TypeApp"},"tag":"ParensInType"}],"tag":"TypeApp"},{"annotation":[],"contents":[["React","Basic","Events"],"EventHandler"],"tag":"TypeConstructor"}],"tag":"TypeApp"}],"tag":"TypeApp"},"visibility":"TypeVarInvisible"},"tag":"ForAll"}},"kind":null,"sourceSpan":{"end":[65,84],"name":".spago/p/react-basic-dom-7.0.0/src/React/Basic/DOM/Events.purs","start":[65,1]},"title":"capture"},{"children":[],"comments":"Like `capture`, but for actions which don't need to extract information from the Event.\n\n__*See also:* `update`, `capture`, `monitor_`__\n","info":{"declType":"value","type":{"annotation":[],"contents":[{"annotation":[],"contents":[{"annotation":[],"contents":[["Prim"],"Function"],"tag":"TypeConstructor"},{"annotation":[],"contents":[{"annotation":[],"contents":[["Effect"],"Effect"],"tag":"TypeConstructor"},{"annotation":[],"contents":[["Data","Unit"],"Unit"],"tag":"TypeConstructor"}],"tag":"TypeApp"}],"tag":"TypeApp"},{"annotation":[],"contents":[["React","Basic","Events"],"EventHandler"],"tag":"TypeConstructor"}],"tag":"TypeApp"}},"kind":null,"sourceSpan":{"end":[71,40],"name":".spago/p/react-basic-dom-7.0.0/src/React/Basic/DOM/Events.purs","start":[71,1]},"title":"capture_"},{"children":[],"comments":"General event fields\n","info":{"declType":"value","type":{"annotation":[],"contents":[{"annotation":[],"contents":[{"annotation":[],"contents":[["React","Basic","Events"],"EventFn"],"tag":"TypeConstructor"},{"annotation":[],"contents":[["React","Basic","Events"],"SyntheticEvent"],"tag":"TypeConstructor"}],"tag":"TypeApp"},{"annotation":[],"contents":[["Prim"],"Boolean"],"tag":"TypeConstructor"}],"tag":"TypeApp"}},"kind":null,"sourceSpan":{"end":[76,42],"name":".spago/p/react-basic-dom-7.0.0/src/React/Basic/DOM/Events.purs","start":[76,1]},"title":"bubbles"},{"children":[],"comments":null,"info":{"declType":"value","type":{"annotation":[],"contents":[{"annotation":[],"contents":[{"annotation":[],"contents":[["React","Basic","Events"],"EventFn"],"tag":"TypeConstructor"},{"annotation":[],"contents":[["React","Basic","Events"],"SyntheticEvent"],"tag":"TypeConstructor"}],"tag":"TypeApp"},{"annotation":[],"contents":[["Prim"],"Boolean"],"tag":"TypeConstructor"}],"tag":"TypeApp"}},"kind":null,"sourceSpan":{"end":[79,45],"name":".spago/p/react-basic-dom-7.0.0/src/React/Basic/DOM/Events.purs","start":[79,1]},"title":"cancelable"},{"children":[],"comments":null,"info":{"declType":"value","type":{"annotation":[],"contents":[{"annotation":[],"contents":[{"annotation":[],"contents":[["React","Basic","Events"],"EventFn"],"tag":"TypeConstructor"},{"annotation":[],"contents":[["React","Basic","Events"],"SyntheticEvent"],"tag":"TypeConstructor"}],"tag":"TypeApp"},{"annotation":[],"contents":{"annotation":[],"contents":[{"annotation":[],"contents":[["Data","Maybe"],"Maybe"],"tag":"TypeConstructor"},{"annotation":[],"contents":[["Prim"],"String"],"tag":"TypeConstructor"}],"tag":"TypeApp"},"tag":"ParensInType"}],"tag":"TypeApp"}},"kind":null,"sourceSpan":{"end":[208,57],"name":".spago/p/react-basic-dom-7.0.0/src/React/Basic/DOM/Events.purs","start":[208,1]},"title":"compositionData"},{"children":[],"comments":null,"info":{"declType":"value","type":{"annotation":[],"contents":[{"annotation":[],"contents":[{"annotation":[],"contents":[["React","Basic","Events"],"EventFn"],"tag":"TypeConstructor"},{"annotation":[],"contents":[["React","Basic","Events"],"SyntheticEvent"],"tag":"TypeConstructor"}],"tag":"TypeApp"},{"annotation":[],"contents":[["Prim"],"Int"],"tag":"TypeConstructor"}],"tag":"TypeApp"}},"kind":null,"sourceSpan":{"end":[82,41],"name":".spago/p/react-basic-dom-7.0.0/src/React/Basic/DOM/Events.purs","start":[82,1]},"title":"eventPhase"},{"children":[],"comments":null,"info":{"declType":"value","type":{"annotation":[],"contents":[["Prim"],"Int"],"tag":"TypeConstructor"}},"kind":null,"sourceSpan":{"end":[85,22],"name":".spago/p/react-basic-dom-7.0.0/src/React/Basic/DOM/Events.purs","start":[85,1]},"title":"eventPhaseNone"},{"children":[],"comments":null,"info":{"declType":"value","type":{"annotation":[],"contents":[["Prim"],"Int"],"tag":"TypeConstructor"}},"kind":null,"sourceSpan":{"end":[88,27],"name":".spago/p/react-basic-dom-7.0.0/src/React/Basic/DOM/Events.purs","start":[88,1]},"title":"eventPhaseCapturing"},{"children":[],"comments":null,"info":{"declType":"value","type":{"annotation":[],"contents":[["Prim"],"Int"],"tag":"TypeConstructor"}},"kind":null,"sourceSpan":{"end":[91,26],"name":".spago/p/react-basic-dom-7.0.0/src/React/Basic/DOM/Events.purs","start":[91,1]},"title":"eventPhaseAtTarget"},{"children":[],"comments":null,"info":{"declType":"value","type":{"annotation":[],"contents":[["Prim"],"Int"],"tag":"TypeConstructor"}},"kind":null,"sourceSpan":{"end":[94,26],"name":".spago/p/react-basic-dom-7.0.0/src/React/Basic/DOM/Events.purs","start":[94,1]},"title":"eventPhaseBubbling"},{"children":[],"comments":null,"info":{"declType":"value","type":{"annotation":[],"contents":[{"annotation":[],"contents":[{"annotation":[],"contents":[["React","Basic","Events"],"EventFn"],"tag":"TypeConstructor"},{"annotation":[],"contents":[["React","Basic","Events"],"SyntheticEvent"],"tag":"TypeConstructor"}],"tag":"TypeApp"},{"annotation":[],"contents":[["Prim"],"Boolean"],"tag":"TypeConstructor"}],"tag":"TypeApp"}},"kind":null,"sourceSpan":{"end":[97,44],"name":".spago/p/react-basic-dom-7.0.0/src/React/Basic/DOM/Events.purs","start":[97,1]},"title":"isTrusted"},{"children":[],"comments":null,"info":{"declType":"value","type":{"annotation":[],"contents":[{"annotation":[],"contents":[{"annotation":[],"contents":[["React","Basic","Events"],"EventFn"],"tag":"TypeConstructor"},{"annotation":[],"contents":[["React","Basic","Events"],"SyntheticEvent"],"tag":"TypeConstructor"}],"tag":"TypeApp"},{"annotation":[],"contents":[["Web","Event","Internal","Types"],"Event"],"tag":"TypeConstructor"}],"tag":"TypeApp"}},"kind":null,"sourceSpan":{"end":[100,44],"name":".spago/p/react-basic-dom-7.0.0/src/React/Basic/DOM/Events.purs","start":[100,1]},"title":"nativeEvent"},{"children":[],"comments":null,"info":{"declType":"value","type":{"annotation":[],"contents":[{"annotation":[],"contents":[{"annotation":[],"contents":[["React","Basic","Events"],"EventFn"],"tag":"TypeConstructor"},{"annotation":[],"contents":[["React","Basic","Events"],"SyntheticEvent"],"tag":"TypeConstructor"}],"tag":"TypeApp"},{"annotation":[],"contents":[["React","Basic","Events"],"SyntheticEvent"],"tag":"TypeConstructor"}],"tag":"TypeApp"}},"kind":null,"sourceSpan":{"end":[103,56],"name":".spago/p/react-basic-dom-7.0.0/src/React/Basic/DOM/Events.purs","start":[103,1]},"title":"preventDefault"},{"children":[],"comments":null,"info":{"declType":"value","type":{"annotation":[],"contents":[{"annotation":[],"contents":[{"annotation":[],"contents":[["React","Basic","Events"],"EventFn"],"tag":"TypeConstructor"},{"annotation":[],"contents":[["React","Basic","Events"],"SyntheticEvent"],"tag":"TypeConstructor"}],"tag":"TypeApp"},{"annotation":[],"contents":[["Prim"],"Boolean"],"tag":"TypeConstructor"}],"tag":"TypeApp"}},"kind":null,"sourceSpan":{"end":[108,53],"name":".spago/p/react-basic-dom-7.0.0/src/React/Basic/DOM/Events.purs","start":[108,1]},"title":"isDefaultPrevented"},{"children":[],"comments":null,"info":{"declType":"value","type":{"annotation":[],"contents":[{"annotation":[],"contents":[{"annotation":[],"contents":[["React","Basic","Events"],"EventFn"],"tag":"TypeConstructor"},{"annotation":[],"contents":[["React","Basic","Events"],"SyntheticEvent"],"tag":"TypeConstructor"}],"tag":"TypeApp"},{"annotation":[],"contents":[["React","Basic","Events"],"SyntheticEvent"],"tag":"TypeConstructor"}],"tag":"TypeApp"}},"kind":null,"sourceSpan":{"end":[112,57],"name":".spago/p/react-basic-dom-7.0.0/src/React/Basic/DOM/Events.purs","start":[112,1]},"title":"stopPropagation"},{"children":[],"comments":null,"info":{"declType":"value","type":{"annotation":[],"contents":[{"annotation":[],"contents":[{"annotation":[],"contents":[["React","Basic","Events"],"EventFn"],"tag":"TypeConstructor"},{"annotation":[],"contents":[["React","Basic","Events"],"SyntheticEvent"],"tag":"TypeConstructor"}],"tag":"TypeApp"},{"annotation":[],"contents":[["Prim"],"Boolean"],"tag":"TypeConstructor"}],"tag":"TypeApp"}},"kind":null,"sourceSpan":{"end":[117,55],"name":".spago/p/react-basic-dom-7.0.0/src/React/Basic/DOM/Events.purs","start":[117,1]},"title":"isPropagationStopped"},{"children":[],"comments":null,"info":{"declType":"value","type":{"annotation":[],"contents":[{"annotation":[],"contents":[{"annotation":[],"contents":[["React","Basic","Events"],"EventFn"],"tag":"TypeConstructor"},{"annotation":[],"contents":[["React","Basic","Events"],"SyntheticEvent"],"tag":"TypeConstructor"}],"tag":"TypeApp"},{"annotation":[],"contents":[["Web","Event","Internal","Types"],"EventTarget"],"tag":"TypeConstructor"}],"tag":"TypeApp"}},"kind":null,"sourceSpan":{"end":[121,45],"name":".spago/p/react-basic-dom-7.0.0/src/React/Basic/DOM/Events.purs","start":[121,1]},"title":"target"},{"children":[],"comments":null,"info":{"declType":"value","type":{"annotation":[],"contents":[{"annotation":[],"contents":[{"annotation":[],"contents":[["React","Basic","Events"],"EventFn"],"tag":"TypeConstructor"},{"annotation":[],"contents":[["React","Basic","Events"],"SyntheticEvent"],"tag":"TypeConstructor"}],"tag":"TypeApp"},{"annotation":[],"contents":[["Web","Event","Internal","Types"],"EventTarget"],"tag":"TypeConstructor"}],"tag":"TypeApp"}},"kind":null,"sourceSpan":{"end":[124,52],"name":".spago/p/react-basic-dom-7.0.0/src/React/Basic/DOM/Events.purs","start":[124,1]},"title":"currentTarget"},{"children":[],"comments":null,"info":{"declType":"value","type":{"annotation":[],"contents":[{"annotation":[],"contents":[{"annotation":[],"contents":[["React","Basic","Events"],"EventFn"],"tag":"TypeConstructor"},{"annotation":[],"contents":[["React","Basic","Events"],"SyntheticEvent"],"tag":"TypeConstructor"}],"tag":"TypeApp"},{"annotation":[],"contents":{"annotation":[],"contents":[{"annotation":[],"contents":[["Data","Maybe"],"Maybe"],"tag":"TypeConstructor"},{"annotation":[],"contents":[["Web","Event","Internal","Types"],"EventTarget"],"tag":"TypeConstructor"}],"tag":"TypeApp"},"tag":"ParensInType"}],"tag":"TypeApp"}},"kind":null,"sourceSpan":{"end":[127,60],"name":".spago/p/react-basic-dom-7.0.0/src/React/Basic/DOM/Events.purs","start":[127,1]},"title":"relatedTarget"},{"children":[],"comments":null,"info":{"declType":"value","type":{"annotation":[],"contents":[{"annotation":[],"contents":[{"annotation":[],"contents":[["React","Basic","Events"],"EventFn"],"tag":"TypeConstructor"},{"annotation":[],"contents":[["React","Basic","Events"],"SyntheticEvent"],"tag":"TypeConstructor"}],"tag":"TypeApp"},{"annotation":[],"contents":{"annotation":[],"contents":[{"annotation":[],"contents":[["Data","Maybe"],"Maybe"],"tag":"TypeConstructor"},{"annotation":[],"contents":[["Prim"],"Boolean"],"tag":"TypeConstructor"}],"tag":"TypeApp"},"tag":"ParensInType"}],"tag":"TypeApp"}},"kind":null,"sourceSpan":{"end":[130,56],"name":".spago/p/react-basic-dom-7.0.0/src/React/Basic/DOM/Events.purs","start":[130,1]},"title":"targetChecked"},{"children":[],"comments":null,"info":{"declType":"value","type":{"annotation":[],"contents":[{"annotation":[],"contents":[{"annotation":[],"contents":[["React","Basic","Events"],"EventFn"],"tag":"TypeConstructor"},{"annotation":[],"contents":[["React","Basic","Events"],"SyntheticEvent"],"tag":"TypeConstructor"}],"tag":"TypeApp"},{"annotation":[],"contents":{"annotation":[],"contents":[{"annotation":[],"contents":[["Data","Maybe"],"Maybe"],"tag":"TypeConstructor"},{"annotation":[],"contents":[["Prim"],"String"],"tag":"TypeConstructor"}],"tag":"TypeApp"},"tag":"ParensInType"}],"tag":"TypeApp"}},"kind":null,"sourceSpan":{"end":[133,53],"name":".spago/p/react-basic-dom-7.0.0/src/React/Basic/DOM/Events.purs","start":[133,1]},"title":"targetValue"},{"children":[],"comments":null,"info":{"declType":"value","type":{"annotation":[],"contents":[{"annotation":[],"contents":[{"annotation":[],"contents":[["React","Basic","Events"],"EventFn"],"tag":"TypeConstructor"},{"annotation":[],"contents":[["React","Basic","Events"],"SyntheticEvent"],"tag":"TypeConstructor"}],"tag":"TypeApp"},{"annotation":[],"contents":{"annotation":[],"contents":[{"annotation":[],"contents":[["Data","Maybe"],"Maybe"],"tag":"TypeConstructor"},{"annotation":[],"contents":[["Web","File","FileList"],"FileList"],"tag":"TypeConstructor"}],"tag":"TypeApp"},"tag":"ParensInType"}],"tag":"TypeApp"}},"kind":null,"sourceSpan":{"end":[136,55],"name":".spago/p/react-basic-dom-7.0.0/src/React/Basic/DOM/Events.purs","start":[136,1]},"title":"targetFiles"},{"children":[],"comments":null,"info":{"declType":"value","type":{"annotation":[],"contents":[{"annotation":[],"contents":[{"annotation":[],"contents":[["React","Basic","Events"],"EventFn"],"tag":"TypeConstructor"},{"annotation":[],"contents":[["React","Basic","Events"],"SyntheticEvent"],"tag":"TypeConstructor"}],"tag":"TypeApp"},{"annotation":[],"contents":[["Prim"],"Number"],"tag":"TypeConstructor"}],"tag":"TypeApp"}},"kind":null,"sourceSpan":{"end":[139,43],"name":".spago/p/react-basic-dom-7.0.0/src/React/Basic/DOM/Events.purs","start":[139,1]},"title":"timeStamp"},{"children":[],"comments":null,"info":{"declType":"value","type":{"annotation":[],"contents":[{"annotation":[],"contents":[{"annotation":[],"contents":[["React","Basic","Events"],"EventFn"],"tag":"TypeConstructor"},{"annotation":[],"contents":[["React","Basic","Events"],"SyntheticEvent"],"tag":"TypeConstructor"}],"tag":"TypeApp"},{"annotation":[],"contents":[["Prim"],"String"],"tag":"TypeConstructor"}],"tag":"TypeApp"}},"kind":null,"sourceSpan":{"end":[142,39],"name":".spago/p/react-basic-dom-7.0.0/src/React/Basic/DOM/Events.purs","start":[142,1]},"title":"type_"},{"children":[],"comments":"Keyboard event fields\n","info":{"declType":"value","type":{"annotation":[],"contents":[{"annotation":[],"contents":[{"annotation":[],"contents":[["React","Basic","Events"],"EventFn"],"tag":"TypeConstructor"},{"annotation":[],"contents":[["React","Basic","Events"],"SyntheticEvent"],"tag":"TypeConstructor"}],"tag":"TypeApp"},{"annotation":[],"contents":{"annotation":[],"contents":[{"annotation":[],"contents":[["Data","Maybe"],"Maybe"],"tag":"TypeConstructor"},{"annotation":[],"contents":[["Prim"],"String"],"tag":"TypeConstructor"}],"tag":"TypeApp"},"tag":"ParensInType"}],"tag":"TypeApp"}},"kind":null,"sourceSpan":{"end":[146,45],"name":".spago/p/react-basic-dom-7.0.0/src/React/Basic/DOM/Events.purs","start":[146,1]},"title":"key"},{"children":[],"comments":null,"info":{"declType":"value","type":{"annotation":[],"contents":[{"annotation":[],"contents":[{"annotation":[],"contents":[["React","Basic","Events"],"EventFn"],"tag":"TypeConstructor"},{"annotation":[],"contents":[["React","Basic","Events"],"SyntheticEvent"],"tag":"TypeConstructor"}],"tag":"TypeApp"},{"annotation":[],"contents":{"annotation":[],"contents":[{"annotation":[],"contents":[["Data","Maybe"],"Maybe"],"tag":"TypeConstructor"},{"annotation":[],"contents":[["Prim"],"String"],"tag":"TypeConstructor"}],"tag":"TypeApp"},"tag":"ParensInType"}],"tag":"TypeApp"}},"kind":null,"sourceSpan":{"end":[149,46],"name":".spago/p/react-basic-dom-7.0.0/src/React/Basic/DOM/Events.purs","start":[149,1]},"title":"code"},{"children":[],"comments":null,"info":{"declType":"value","type":{"annotation":[],"contents":[{"annotation":[],"contents":[{"annotation":[],"contents":[["React","Basic","Events"],"EventFn"],"tag":"TypeConstructor"},{"annotation":[],"contents":[["React","Basic","Events"],"SyntheticEvent"],"tag":"TypeConstructor"}],"tag":"TypeApp"},{"annotation":[],"contents":{"annotation":[],"contents":[{"annotation":[],"contents":[["Data","Maybe"],"Maybe"],"tag":"TypeConstructor"},{"annotation":[],"contents":[["Prim"],"String"],"tag":"TypeConstructor"}],"tag":"TypeApp"},"tag":"ParensInType"}],"tag":"TypeApp"}},"kind":null,"sourceSpan":{"end":[152,46],"name":".spago/p/react-basic-dom-7.0.0/src/React/Basic/DOM/Events.purs","start":[152,1]},"title":"char"},{"children":[],"comments":null,"info":{"declType":"value","type":{"annotation":[],"contents":[{"annotation":[],"contents":[{"annotation":[],"contents":[["React","Basic","Events"],"EventFn"],"tag":"TypeConstructor"},{"annotation":[],"contents":[["React","Basic","Events"],"SyntheticEvent"],"tag":"TypeConstructor"}],"tag":"TypeApp"},{"annotation":[],"contents":{"annotation":[],"contents":[{"annotation":[],"contents":[["Data","Maybe"],"Maybe"],"tag":"TypeConstructor"},{"annotation":[],"contents":[["Prim"],"Number"],"tag":"TypeConstructor"}],"tag":"TypeApp"},"tag":"ParensInType"}],"tag":"TypeApp"}},"kind":null,"sourceSpan":{"end":[155,50],"name":".spago/p/react-basic-dom-7.0.0/src/React/Basic/DOM/Events.purs","start":[155,1]},"title":"location"},{"children":[],"comments":null,"info":{"declType":"value","type":{"annotation":[],"contents":[{"annotation":[],"contents":[{"annotation":[],"contents":[["React","Basic","Events"],"EventFn"],"tag":"TypeConstructor"},{"annotation":[],"contents":[["React","Basic","Events"],"SyntheticEvent"],"tag":"TypeConstructor"}],"tag":"TypeApp"},{"annotation":[],"contents":{"annotation":[],"contents":[{"annotation":[],"contents":[["Data","Maybe"],"Maybe"],"tag":"TypeConstructor"},{"annotation":[],"contents":[["Prim"],"Boolean"],"tag":"TypeConstructor"}],"tag":"TypeApp"},"tag":"ParensInType"}],"tag":"TypeApp"}},"kind":null,"sourceSpan":{"end":[158,49],"name":".spago/p/react-basic-dom-7.0.0/src/React/Basic/DOM/Events.purs","start":[158,1]},"title":"repeat"},{"children":[],"comments":null,"info":{"declType":"value","type":{"annotation":[],"contents":[{"annotation":[],"contents":[{"annotation":[],"contents":[["React","Basic","Events"],"EventFn"],"tag":"TypeConstructor"},{"annotation":[],"contents":[["React","Basic","Events"],"SyntheticEvent"],"tag":"TypeConstructor"}],"tag":"TypeApp"},{"annotation":[],"contents":{"annotation":[],"contents":[{"annotation":[],"contents":[["Data","Maybe"],"Maybe"],"tag":"TypeConstructor"},{"annotation":[],"contents":[["Prim"],"String"],"tag":"TypeConstructor"}],"tag":"TypeApp"},"tag":"ParensInType"}],"tag":"TypeApp"}},"kind":null,"sourceSpan":{"end":[161,48],"name":".spago/p/react-basic-dom-7.0.0/src/React/Basic/DOM/Events.purs","start":[161,1]},"title":"locale"},{"children":[],"comments":null,"info":{"declType":"value","type":{"annotation":[],"contents":[{"annotation":[],"contents":[{"annotation":[],"contents":[["React","Basic","Events"],"EventFn"],"tag":"TypeConstructor"},{"annotation":[],"contents":[["React","Basic","Events"],"SyntheticEvent"],"tag":"TypeConstructor"}],"tag":"TypeApp"},{"annotation":[],"contents":{"annotation":[],"contents":[{"annotation":[],"contents":[["Data","Maybe"],"Maybe"],"tag":"TypeConstructor"},{"annotation":[],"contents":[["Prim"],"Boolean"],"tag":"TypeConstructor"}],"tag":"TypeApp"},"tag":"ParensInType"}],"tag":"TypeApp"}},"kind":null,"sourceSpan":{"end":[191,50],"name":".spago/p/react-basic-dom-7.0.0/src/React/Basic/DOM/Events.purs","start":[191,1]},"title":"ctrlKey"},{"children":[],"comments":null,"info":{"declType":"value","type":{"annotation":[],"contents":[{"annotation":[],"contents":[{"annotation":[],"contents":[["React","Basic","Events"],"EventFn"],"tag":"TypeConstructor"},{"annotation":[],"contents":[["React","Basic","Events"],"SyntheticEvent"],"tag":"TypeConstructor"}],"tag":"TypeApp"},{"annotation":[],"contents":{"annotation":[],"contents":[{"annotation":[],"contents":[["Data","Maybe"],"Maybe"],"tag":"TypeConstructor"},{"annotation":[],"contents":[["Prim"],"Boolean"],"tag":"TypeConstructor"}],"tag":"TypeApp"},"tag":"ParensInType"}],"tag":"TypeApp"}},"kind":null,"sourceSpan":{"end":[194,51],"name":".spago/p/react-basic-dom-7.0.0/src/React/Basic/DOM/Events.purs","start":[194,1]},"title":"shiftKey"},{"children":[],"comments":null,"info":{"declType":"value","type":{"annotation":[],"contents":[{"annotation":[],"contents":[{"annotation":[],"contents":[["React","Basic","Events"],"EventFn"],"tag":"TypeConstructor"},{"annotation":[],"contents":[["React","Basic","Events"],"SyntheticEvent"],"tag":"TypeConstructor"}],"tag":"TypeApp"},{"annotation":[],"contents":{"annotation":[],"contents":[{"annotation":[],"contents":[["Data","Maybe"],"Maybe"],"tag":"TypeConstructor"},{"annotation":[],"contents":[["Prim"],"Boolean"],"tag":"TypeConstructor"}],"tag":"TypeApp"},"tag":"ParensInType"}],"tag":"TypeApp"}},"kind":null,"sourceSpan":{"end":[197,49],"name":".spago/p/react-basic-dom-7.0.0/src/React/Basic/DOM/Events.purs","start":[197,1]},"title":"altKey"},{"children":[],"comments":null,"info":{"declType":"value","type":{"annotation":[],"contents":[{"annotation":[],"contents":[{"annotation":[],"contents":[["React","Basic","Events"],"EventFn"],"tag":"TypeConstructor"},{"annotation":[],"contents":[["React","Basic","Events"],"SyntheticEvent"],"tag":"TypeConstructor"}],"tag":"TypeApp"},{"annotation":[],"contents":{"annotation":[],"contents":[{"annotation":[],"contents":[["Data","Maybe"],"Maybe"],"tag":"TypeConstructor"},{"annotation":[],"contents":[["Prim"],"Boolean"],"tag":"TypeConstructor"}],"tag":"TypeApp"},"tag":"ParensInType"}],"tag":"TypeApp"}},"kind":null,"sourceSpan":{"end":[200,50],"name":".spago/p/react-basic-dom-7.0.0/src/React/Basic/DOM/Events.purs","start":[200,1]},"title":"metaKey"},{"children":[],"comments":"Mouse event fields\n","info":{"declType":"value","type":{"annotation":[],"contents":[{"annotation":[],"contents":[{"annotation":[],"contents":[["React","Basic","Events"],"EventFn"],"tag":"TypeConstructor"},{"annotation":[],"contents":[["React","Basic","Events"],"SyntheticEvent"],"tag":"TypeConstructor"}],"tag":"TypeApp"},{"annotation":[],"contents":{"annotation":[],"contents":[{"annotation":[],"contents":[["Data","Maybe"],"Maybe"],"tag":"TypeConstructor"},{"annotation":[],"contents":[["Prim"],"Int"],"tag":"TypeConstructor"}],"tag":"TypeApp"},"tag":"ParensInType"}],"tag":"TypeApp"}},"kind":null,"sourceSpan":{"end":[165,45],"name":".spago/p/react-basic-dom-7.0.0/src/React/Basic/DOM/Events.purs","start":[165,1]},"title":"detail"},{"children":[],"comments":null,"info":{"declType":"value","type":{"annotation":[],"contents":[{"annotation":[],"contents":[{"annotation":[],"contents":[["React","Basic","Events"],"EventFn"],"tag":"TypeConstructor"},{"annotation":[],"contents":[["React","Basic","Events"],"SyntheticEvent"],"tag":"TypeConstructor"}],"tag":"TypeApp"},{"annotation":[],"contents":{"annotation":[],"contents":[{"annotation":[],"contents":[["Data","Maybe"],"Maybe"],"tag":"TypeConstructor"},{"annotation":[],"contents":[["Prim"],"Number"],"tag":"TypeConstructor"}],"tag":"TypeApp"},"tag":"ParensInType"}],"tag":"TypeApp"}},"kind":null,"sourceSpan":{"end":[168,49],"name":".spago/p/react-basic-dom-7.0.0/src/React/Basic/DOM/Events.purs","start":[168,1]},"title":"screenX"},{"children":[],"comments":null,"info":{"declType":"value","type":{"annotation":[],"contents":[{"annotation":[],"contents":[{"annotation":[],"contents":[["React","Basic","Events"],"EventFn"],"tag":"TypeConstructor"},{"annotation":[],"contents":[["React","Basic","Events"],"SyntheticEvent"],"tag":"TypeConstructor"}],"tag":"TypeApp"},{"annotation":[],"contents":{"annotation":[],"contents":[{"annotation":[],"contents":[["Data","Maybe"],"Maybe"],"tag":"TypeConstructor"},{"annotation":[],"contents":[["Prim"],"Number"],"tag":"TypeConstructor"}],"tag":"TypeApp"},"tag":"ParensInType"}],"tag":"TypeApp"}},"kind":null,"sourceSpan":{"end":[171,49],"name":".spago/p/react-basic-dom-7.0.0/src/React/Basic/DOM/Events.purs","start":[171,1]},"title":"screenY"},{"children":[],"comments":null,"info":{"declType":"value","type":{"annotation":[],"contents":[{"annotation":[],"contents":[{"annotation":[],"contents":[["React","Basic","Events"],"EventFn"],"tag":"TypeConstructor"},{"annotation":[],"contents":[["React","Basic","Events"],"SyntheticEvent"],"tag":"TypeConstructor"}],"tag":"TypeApp"},{"annotation":[],"contents":{"annotation":[],"contents":[{"annotation":[],"contents":[["Data","Maybe"],"Maybe"],"tag":"TypeConstructor"},{"annotation":[],"contents":[["Prim"],"Number"],"tag":"TypeConstructor"}],"tag":"TypeApp"},"tag":"ParensInType"}],"tag":"TypeApp"}},"kind":null,"sourceSpan":{"end":[174,49],"name":".spago/p/react-basic-dom-7.0.0/src/React/Basic/DOM/Events.purs","start":[174,1]},"title":"clientX"},{"children":[],"comments":null,"info":{"declType":"value","type":{"annotation":[],"contents":[{"annotation":[],"contents":[{"annotation":[],"contents":[["React","Basic","Events"],"EventFn"],"tag":"TypeConstructor"},{"annotation":[],"contents":[["React","Basic","Events"],"SyntheticEvent"],"tag":"TypeConstructor"}],"tag":"TypeApp"},{"annotation":[],"contents":{"annotation":[],"contents":[{"annotation":[],"contents":[["Data","Maybe"],"Maybe"],"tag":"TypeConstructor"},{"annotation":[],"contents":[["Prim"],"Number"],"tag":"TypeConstructor"}],"tag":"TypeApp"},"tag":"ParensInType"}],"tag":"TypeApp"}},"kind":null,"sourceSpan":{"end":[177,49],"name":".spago/p/react-basic-dom-7.0.0/src/React/Basic/DOM/Events.purs","start":[177,1]},"title":"clientY"},{"children":[],"comments":null,"info":{"declType":"value","type":{"annotation":[],"contents":[{"annotation":[],"contents":[{"annotation":[],"contents":[["React","Basic","Events"],"EventFn"],"tag":"TypeConstructor"},{"annotation":[],"contents":[["React","Basic","Events"],"SyntheticEvent"],"tag":"TypeConstructor"}],"tag":"TypeApp"},{"annotation":[],"contents":{"annotation":[],"contents":[{"annotation":[],"contents":[["Data","Maybe"],"Maybe"],"tag":"TypeConstructor"},{"annotation":[],"contents":[["Prim"],"Int"],"tag":"TypeConstructor"}],"tag":"TypeApp"},"tag":"ParensInType"}],"tag":"TypeApp"}},"kind":null,"sourceSpan":{"end":[180,45],"name":".spago/p/react-basic-dom-7.0.0/src/React/Basic/DOM/Events.purs","start":[180,1]},"title":"button"},{"children":[],"comments":null,"info":{"declType":"value","type":{"annotation":[],"contents":[{"annotation":[],"contents":[{"annotation":[],"contents":[["React","Basic","Events"],"EventFn"],"tag":"TypeConstructor"},{"annotation":[],"contents":[["React","Basic","Events"],"SyntheticEvent"],"tag":"TypeConstructor"}],"tag":"TypeApp"},{"annotation":[],"contents":{"annotation":[],"contents":[{"annotation":[],"contents":[["Data","Maybe"],"Maybe"],"tag":"TypeConstructor"},{"annotation":[],"contents":[["Prim"],"Int"],"tag":"TypeConstructor"}],"tag":"TypeApp"},"tag":"ParensInType"}],"tag":"TypeApp"}},"kind":null,"sourceSpan":{"end":[183,46],"name":".spago/p/react-basic-dom-7.0.0/src/React/Basic/DOM/Events.purs","start":[183,1]},"title":"buttons"},{"children":[],"comments":"Drag event fields\n","info":{"declType":"value","type":{"annotation":[],"contents":[{"annotation":[],"contents":[{"annotation":[],"contents":[["React","Basic","Events"],"EventFn"],"tag":"TypeConstructor"},{"annotation":[],"contents":[["React","Basic","Events"],"SyntheticEvent"],"tag":"TypeConstructor"}],"tag":"TypeApp"},{"annotation":[],"contents":{"annotation":[],"contents":[{"annotation":[],"contents":[["Data","Maybe"],"Maybe"],"tag":"TypeConstructor"},{"annotation":[],"contents":[["Web","HTML","Event","DataTransfer"],"DataTransfer"],"tag":"TypeConstructor"}],"tag":"TypeApp"},"tag":"ParensInType"}],"tag":"TypeApp"}},"kind":null,"sourceSpan":{"end":[187,60],"name":".spago/p/react-basic-dom-7.0.0/src/React/Basic/DOM/Events.purs","start":[187,1]},"title":"dataTransfer"},{"children":[],"comments":null,"info":{"declType":"value","type":{"annotation":[],"contents":[{"annotation":[],"contents":[{"annotation":[],"contents":[["React","Basic","Events"],"EventFn"],"tag":"TypeConstructor"},{"annotation":[],"contents":[["React","Basic","Events"],"SyntheticEvent"],"tag":"TypeConstructor"}],"tag":"TypeApp"},{"annotation":[],"contents":{"annotation":[],"contents":[{"annotation":[],"contents":[["Data","Maybe"],"Maybe"],"tag":"TypeConstructor"},{"annotation":[],"contents":[["Web","HTML","Event","DataTransfer"],"DataTransfer"],"tag":"TypeConstructor"}],"tag":"TypeApp"},"tag":"ParensInType"}],"tag":"TypeApp"}},"kind":null,"sourceSpan":{"end":[204,61],"name":".spago/p/react-basic-dom-7.0.0/src/React/Basic/DOM/Events.purs","start":[204,1]},"title":"clipboardData"}],"name":"React.Basic.DOM.Events","reExports":[]}