{"builtWith":"0.15.15","comments":[],"decls":[{"annotation":{"meta":null,"sourceSpan":{"end":[0,0],"start":[0,0]}},"bindType":"NonRec","expression":{"abstraction":{"annotation":{"meta":{"metaType":"IsForeign"},"sourceSpan":{"end":[6,26],"start":[6,24]}},"type":"Var","value":{"identifier":"append","moduleName":["Data","Semigroup"]}},"annotation":{"meta":{"metaType":"IsSyntheticApp"},"sourceSpan":{"end":[6,39],"start":[6,17]}},"argument":{"annotation":{"meta":null,"sourceSpan":{"end":[0,0],"start":[0,0]}},"type":"Var","value":{"identifier":"semigroupString","moduleName":["Data","Semigroup"]}},"type":"App"},"identifier":"append"},{"annotation":{"meta":null,"sourceSpan":{"end":[63,20],"start":[63,1]}},"bindType":"NonRec","expression":{"annotation":{"meta":null,"sourceSpan":{"end":[64,30],"start":[64,13]}},"type":"Literal","value":{"literalType":"StringLiteral","value":"mask-triangle-4"}},"identifier":"triangle4"},{"annotation":{"meta":null,"sourceSpan":{"end":[60,20],"start":[60,1]}},"bindType":"NonRec","expression":{"annotation":{"meta":null,"sourceSpan":{"end":[61,30],"start":[61,13]}},"type":"Literal","value":{"literalType":"StringLiteral","value":"mask-triangle-3"}},"identifier":"triangle3"},{"annotation":{"meta":null,"sourceSpan":{"end":[57,20],"start":[57,1]}},"bindType":"NonRec","expression":{"annotation":{"meta":null,"sourceSpan":{"end":[58,30],"start":[58,13]}},"type":"Literal","value":{"literalType":"StringLiteral","value":"mask-triangle-2"}},"identifier":"triangle2"},{"annotation":{"meta":null,"sourceSpan":{"end":[54,19],"start":[54,1]}},"bindType":"NonRec","expression":{"annotation":{"meta":null,"sourceSpan":{"end":[55,27],"start":[55,12]}},"type":"Literal","value":{"literalType":"StringLiteral","value":"mask-triangle"}},"identifier":"triangle"},{"annotation":{"meta":null,"sourceSpan":{"end":[51,16],"start":[51,1]}},"bindType":"NonRec","expression":{"annotation":{"meta":null,"sourceSpan":{"end":[52,22],"start":[52,9]}},"type":"Literal","value":{"literalType":"StringLiteral","value":"mask-star-2"}},"identifier":"star2"},{"annotation":{"meta":null,"sourceSpan":{"end":[48,15],"start":[48,1]}},"bindType":"NonRec","expression":{"annotation":{"meta":null,"sourceSpan":{"end":[49,19],"start":[49,8]}},"type":"Literal","value":{"literalType":"StringLiteral","value":"mask-star"}},"identifier":"star"},{"annotation":{"meta":null,"sourceSpan":{"end":[9,19],"start":[9,1]}},"bindType":"NonRec","expression":{"annotation":{"meta":null,"sourceSpan":{"end":[10,27],"start":[10,12]}},"type":"Literal","value":{"literalType":"StringLiteral","value":"mask-squircle"}},"identifier":"squircle"},{"annotation":{"meta":null,"sourceSpan":{"end":[30,17],"start":[30,1]}},"bindType":"NonRec","expression":{"annotation":{"meta":null,"sourceSpan":{"end":[31,23],"start":[31,10]}},"type":"Literal","value":{"literalType":"StringLiteral","value":"mask-square"}},"identifier":"square"},{"annotation":{"meta":null,"sourceSpan":{"end":[24,19],"start":[24,1]}},"bindType":"NonRec","expression":{"annotation":{"meta":null,"sourceSpan":{"end":[25,27],"start":[25,12]}},"type":"Literal","value":{"literalType":"StringLiteral","value":"mask-pentagon"}},"identifier":"pentagon"},{"annotation":{"meta":null,"sourceSpan":{"end":[45,25],"start":[45,1]}},"bindType":"NonRec","expression":{"annotation":{"meta":null,"sourceSpan":{"end":[46,40],"start":[46,18]}},"type":"Literal","value":{"literalType":"StringLiteral","value":"mask-parallelogram-4"}},"identifier":"parallelogram4"},{"annotation":{"meta":null,"sourceSpan":{"end":[42,25],"start":[42,1]}},"bindType":"NonRec","expression":{"annotation":{"meta":null,"sourceSpan":{"end":[43,40],"start":[43,18]}},"type":"Literal","value":{"literalType":"StringLiteral","value":"mask-parallelogram-3"}},"identifier":"parallelogram3"},{"annotation":{"meta":null,"sourceSpan":{"end":[39,25],"start":[39,1]}},"bindType":"NonRec","expression":{"annotation":{"meta":null,"sourceSpan":{"end":[40,40],"start":[40,18]}},"type":"Literal","value":{"literalType":"StringLiteral","value":"mask-parallelogram-2"}},"identifier":"parallelogram2"},{"annotation":{"meta":null,"sourceSpan":{"end":[36,24],"start":[36,1]}},"bindType":"NonRec","expression":{"annotation":{"meta":null,"sourceSpan":{"end":[37,37],"start":[37,17]}},"type":"Literal","value":{"literalType":"StringLiteral","value":"mask-parallelogram"}},"identifier":"parallelogram"},{"annotation":{"meta":null,"sourceSpan":{"end":[5,28],"start":[5,1]}},"bindType":"NonRec","expression":{"annotation":{"meta":null,"sourceSpan":{"end":[5,28],"start":[5,1]}},"argument":"shape","body":{"abstraction":{"abstraction":{"annotation":{"meta":null,"sourceSpan":{"end":[0,0],"start":[0,0]}},"type":"Var","value":{"identifier":"append","moduleName":["DaisyUI","Mask"]}},"annotation":{"meta":null,"sourceSpan":{"end":[6,39],"start":[6,17]}},"argument":{"annotation":{"meta":null,"sourceSpan":{"end":[6,23],"start":[6,17]}},"type":"Literal","value":{"literalType":"StringLiteral","value":"mask"}},"type":"App"},"annotation":{"meta":null,"sourceSpan":{"end":[6,39],"start":[6,17]}},"argument":{"abstraction":{"abstraction":{"annotation":{"meta":null,"sourceSpan":{"end":[0,0],"start":[0,0]}},"type":"Var","value":{"identifier":"append","moduleName":["DaisyUI","Mask"]}},"annotation":{"meta":null,"sourceSpan":{"end":[6,39],"start":[6,17]}},"argument":{"annotation":{"meta":null,"sourceSpan":{"end":[6,30],"start":[6,27]}},"type":"Literal","value":{"literalType":"StringLiteral","value":" "}},"type":"App"},"annotation":{"meta":null,"sourceSpan":{"end":[6,39],"start":[6,17]}},"argument":{"annotation":{"meta":null,"sourceSpan":{"end":[6,39],"start":[6,34]}},"type":"Var","value":{"identifier":"shape","sourcePos":[6,1]}},"type":"App"},"type":"App"},"type":"Abs"},"identifier":"maskCls"},{"annotation":{"meta":null,"sourceSpan":{"end":[18,19],"start":[18,1]}},"bindType":"NonRec","expression":{"annotation":{"meta":null,"sourceSpan":{"end":[19,28],"start":[19,12]}},"type":"Literal","value":{"literalType":"StringLiteral","value":"mask-hexagon-2"}},"identifier":"hexagon2"},{"annotation":{"meta":null,"sourceSpan":{"end":[15,18],"start":[15,1]}},"bindType":"NonRec","expression":{"annotation":{"meta":null,"sourceSpan":{"end":[16,25],"start":[16,11]}},"type":"Literal","value":{"literalType":"StringLiteral","value":"mask-hexagon"}},"identifier":"hexagon"},{"annotation":{"meta":null,"sourceSpan":{"end":[12,16],"start":[12,1]}},"bindType":"NonRec","expression":{"annotation":{"meta":null,"sourceSpan":{"end":[13,21],"start":[13,9]}},"type":"Literal","value":{"literalType":"StringLiteral","value":"mask-heart"}},"identifier":"heart"},{"annotation":{"meta":null,"sourceSpan":{"end":[69,16],"start":[69,1]}},"bindType":"NonRec","expression":{"annotation":{"meta":null,"sourceSpan":{"end":[70,22],"start":[70,9]}},"type":"Literal","value":{"literalType":"StringLiteral","value":"mask-half-2"}},"identifier":"half2"},{"annotation":{"meta":null,"sourceSpan":{"end":[66,16],"start":[66,1]}},"bindType":"NonRec","expression":{"annotation":{"meta":null,"sourceSpan":{"end":[67,22],"start":[67,9]}},"type":"Literal","value":{"literalType":"StringLiteral","value":"mask-half-1"}},"identifier":"half1"},{"annotation":{"meta":null,"sourceSpan":{"end":[27,18],"start":[27,1]}},"bindType":"NonRec","expression":{"annotation":{"meta":null,"sourceSpan":{"end":[28,25],"start":[28,11]}},"type":"Literal","value":{"literalType":"StringLiteral","value":"mask-diamond"}},"identifier":"diamond"},{"annotation":{"meta":null,"sourceSpan":{"end":[21,18],"start":[21,1]}},"bindType":"NonRec","expression":{"annotation":{"meta":null,"sourceSpan":{"end":[22,25],"start":[22,11]}},"type":"Literal","value":{"literalType":"StringLiteral","value":"mask-decagon"}},"identifier":"decagon"},{"annotation":{"meta":null,"sourceSpan":{"end":[33,17],"start":[33,1]}},"bindType":"NonRec","expression":{"annotation":{"meta":null,"sourceSpan":{"end":[34,23],"start":[34,10]}},"type":"Literal","value":{"literalType":"StringLiteral","value":"mask-circle"}},"identifier":"circle"}],"exports":["maskCls","squircle","heart","hexagon","hexagon2","decagon","pentagon","diamond","square","circle","parallelogram","parallelogram2","parallelogram3","parallelogram4","star","star2","triangle","triangle2","triangle3","triangle4","half1","half2"],"foreign":[],"imports":[{"annotation":{"meta":null,"sourceSpan":{"end":[70,22],"start":[1,1]}},"moduleName":["Data","Semigroup"]},{"annotation":{"meta":null,"sourceSpan":{"end":[3,15],"start":[3,1]}},"moduleName":["Prelude"]},{"annotation":{"meta":null,"sourceSpan":{"end":[70,22],"start":[1,1]}},"moduleName":["Prim"]}],"moduleName":["DaisyUI","Mask"],"modulePath":"src/DaisyUI/Mask.purs","reExports":{},"sourceSpan":{"end":[70,22],"start":[1,1]}}