{"comments":null,"declarations":[{"children":[],"comments":"The `<cite>` element in HTML, represents a reference to a creative work.\nIt must include the title of a work or a URL reference, which may be in an abbreviated form\naccording to the conventions used for the addition of citation metadata.\n\n#### Example:\n```purescript\ncite { } \"The Title of the Work\"\n```\n","info":{"declType":"value","type":{"annotation":[],"contents":[{"annotation":[],"contents":[["Yoga","React","DOM","Internal"],"FFIComponent"],"tag":"TypeConstructor"},{"annotation":[],"contents":[["Yoga","React","DOM","Attributes"],"BaseAttributes"],"tag":"TypeConstructor"}],"tag":"TypeApp"}},"kind":null,"sourceSpan":{"end":[16,36],"name":".spago/p/yoga-react-dom-1.0.3/src/Yoga/React/DOM/HTML/Cite.purs","start":[16,1]},"title":"cite"}],"name":"Yoga.React.DOM.HTML.Cite","reExports":[]}